py_chessboardjs/__init__.py
py_chessboardjs/index.html
py_chessboardjs/start.py
py_chessboardjs/bootstrap-5.3.0-dist/css/bootstrap-grid.css
py_chessboardjs/bootstrap-5.3.0-dist/css/bootstrap-grid.css.map
py_chessboardjs/bootstrap-5.3.0-dist/css/bootstrap-grid.min.css
py_chessboardjs/bootstrap-5.3.0-dist/css/bootstrap-grid.min.css.map
py_chessboardjs/bootstrap-5.3.0-dist/css/bootstrap-grid.rtl.css
py_chessboardjs/bootstrap-5.3.0-dist/css/bootstrap-grid.rtl.css.map
py_chessboardjs/bootstrap-5.3.0-dist/css/bootstrap-grid.rtl.min.css
py_chessboardjs/bootstrap-5.3.0-dist/css/bootstrap-grid.rtl.min.css.map
py_chessboardjs/bootstrap-5.3.0-dist/css/bootstrap-reboot.css
py_chessboardjs/bootstrap-5.3.0-dist/css/bootstrap-reboot.css.map
py_chessboardjs/bootstrap-5.3.0-dist/css/bootstrap-reboot.min.css
py_chessboardjs/bootstrap-5.3.0-dist/css/bootstrap-reboot.min.css.map
py_chessboardjs/bootstrap-5.3.0-dist/css/bootstrap-reboot.rtl.css
py_chessboardjs/bootstrap-5.3.0-dist/css/bootstrap-reboot.rtl.css.map
py_chessboardjs/bootstrap-5.3.0-dist/css/bootstrap-reboot.rtl.min.css
py_chessboardjs/bootstrap-5.3.0-dist/css/bootstrap-reboot.rtl.min.css.map
py_chessboardjs/bootstrap-5.3.0-dist/css/bootstrap-utilities.css
py_chessboardjs/bootstrap-5.3.0-dist/css/bootstrap-utilities.css.map
py_chessboardjs/bootstrap-5.3.0-dist/css/bootstrap-utilities.min.css
py_chessboardjs/bootstrap-5.3.0-dist/css/bootstrap-utilities.min.css.map
py_chessboardjs/bootstrap-5.3.0-dist/css/bootstrap-utilities.rtl.css
py_chessboardjs/bootstrap-5.3.0-dist/css/bootstrap-utilities.rtl.css.map
py_chessboardjs/bootstrap-5.3.0-dist/css/bootstrap-utilities.rtl.min.css
py_chessboardjs/bootstrap-5.3.0-dist/css/bootstrap-utilities.rtl.min.css.map
py_chessboardjs/bootstrap-5.3.0-dist/css/bootstrap.css
py_chessboardjs/bootstrap-5.3.0-dist/css/bootstrap.css.map
py_chessboardjs/bootstrap-5.3.0-dist/css/bootstrap.min.css
py_chessboardjs/bootstrap-5.3.0-dist/css/bootstrap.min.css.map
py_chessboardjs-0.0.2.dist-info/LICENSE
py_chessboardjs-0.0.2.dist-info/METADATA
py_chessboardjs-0.0.2.dist-info/WHEEL
py_chessboardjs-0.0.2.dist-info/entry_points.txt
py_chessboardjs-0.0.2.dist-info/top_level.txt
py_chessboardjs-0.0.2.dist-info/RECORD
