Metadata-Version: 2.1
Name: py-chessboardjs
Version: 0.0.2
Summary: Chess GUI using pywebview and chessboard.js.
Home-page: https://github.com/akuroiwa/py-chessboardjs
Author: Akihiro Kuroiwa, ChatGPT of OpenAI
Author-email: akuroiwa@env-reform.com, 
License: GNU/GPLv3+
Keywords: evolutionary algorithms,genetic programming,gp,chess,fen,pgn
Platform: any
Classifier: Development Status :: 3 - Alpha
Classifier: Intended Audience :: Developers
Classifier: Intended Audience :: End Users/Desktop
Classifier: Intended Audience :: Science/Research
Classifier: Operating System :: OS Independent
Classifier: License :: OSI Approved :: GNU General Public License v3 or later (GPLv3+)
Classifier: Programming Language :: Python :: 3 :: Only
Classifier: Topic :: Scientific/Engineering
Classifier: Topic :: Software Development :: User Interfaces
Classifier: Topic :: Games/Entertainment :: Board Games
Classifier: Topic :: Software Development :: Libraries :: Python Modules
Requires-Python: >=3.7, !=3.10.*
License-File: LICENSE
Requires-Dist: chess
Requires-Dist: chess-ant
Requires-Dist: pywebview
Provides-Extra: cef
Requires-Dist: pywebview[cef] ; extra == 'cef'
Provides-Extra: gtk
Requires-Dist: pywebview[gtk] ; extra == 'gtk'
Provides-Extra: qt
Requires-Dist: pywebview[qt] ; extra == 'qt'
